alphaflow/__init__.py
alphaflow/enums.py
alphaflow/utils.py
alphaflow/analyzers/__init__.py
alphaflow/analyzers/default_analyzer.py
alphaflow/brokers/__init__.py
alphaflow/brokers/simple_broker.py
alphaflow/commission_models/__init__.py
alphaflow/commission_models/fixed_commission_model.py
alphaflow/commission_models/per_share_commission_model.py
alphaflow/commission_models/percentage_commission_model.py
alphaflow/data_feeds/__init__.py
alphaflow/data_feeds/alpha_vantage_data_feed.py
alphaflow/data_feeds/csv_data_feed.py
alphaflow/data_feeds/fmp_data_feed.py
alphaflow/data_feeds/polars_data_feed.py
alphaflow/data_feeds/polygon_data_feed.py
alphaflow/event_bus/event_bus.py
alphaflow/event_bus/event_queue.py
alphaflow/event_bus/subscriber.py
alphaflow/events/__init__.py
alphaflow/events/event.py
alphaflow/events/fill_event.py
alphaflow/events/market_data_event.py
alphaflow/events/order_event.py
alphaflow/slippage_models/__init__.py
alphaflow/slippage_models/fixed_slippage_model.py
alphaflow/strategies/__init__.py
alphaflow/strategies/buy_and_hold_strategy.py
alphaflow-0.3.0.dist-info/METADATA
alphaflow-0.3.0.dist-info/WHEEL
alphaflow-0.3.0.dist-info/licenses/LICENSE
alphaflow-0.3.0.dist-info/RECORD
