Metadata-Version: 2.4
Name: alphaflow
Version: 0.3.0
Summary: AlphaFlow is a Python-based, event-driven backtesting framework designed for professional-grade trading research and strategy development.
Project-URL: Homepage, https://github.com/brandonschabell/alphaflow
Project-URL: Repository, https://github.com/brandonschabell/alphaflow
Project-URL: Issues, https://github.com/brandonschabell/alphaflow/issues
Project-URL: Changelog, https://github.com/brandonschabell/alphaflow/blob/main/CHANGELOG.md
Author-email: Brandon Schabell <brandonschabell@gmail.com>
License: MIT
License-File: LICENSE
Classifier: Development Status :: 4 - Beta
Classifier: Environment :: Web Environment
Classifier: Intended Audience :: Developers
Classifier: Intended Audience :: Financial and Insurance Industry
Classifier: Intended Audience :: Science/Research
Classifier: License :: OSI Approved :: MIT License
Classifier: Operating System :: OS Independent
Classifier: Programming Language :: Python :: 3.10
Classifier: Programming Language :: Python :: 3.11
Classifier: Programming Language :: Python :: 3.12
Classifier: Programming Language :: Python :: 3.13
Classifier: Programming Language :: Python :: 3.14
Classifier: Topic :: Office/Business :: Financial
Classifier: Topic :: Scientific/Engineering :: Information Analysis
Classifier: Topic :: Software Development
Requires-Python: >=3.10
Requires-Dist: httpx>=0.28.0
Requires-Dist: plotly>=5.0.0
Requires-Dist: polars>=1.0.0
Requires-Dist: python-dotenv>=1.0.0
Requires-Dist: typing-extensions>=4.6.0
